[
  {
    "anonymous": false,
    "inputs": [
      {
        "indexed": false,
        "internalType": "address",
        "name": "previousAdmin",
        "type": "address"
      },
      {
        "indexed": false,
        "internalType": "address",
        "name": "newAdmin",
        "type": "address"
      }
    ],
    "name": "AdminChanged",
    "type": "event"
  },
  {
    "anonymous": false,
    "inputs": [
      {
        "indexed": false,
        "internalType": "uint256",
        "name": "artistId",
        "type": "uint256"
      },
      {
        "indexed": false,
        "internalType": "string",
        "name": "symbol",
        "type": "string"
      },
      {
        "indexed": false,
        "internalType": "string",
        "name": "name",
        "type": "string"
      },
      {
        "indexed": false,
        "internalType": "string",
        "name": "instagram",
        "type": "string"
      },
      {
        "indexed": false,
        "internalType": "string",
        "name": "instagramId",
        "type": "string"
      },
      {
        "indexed": true,
        "internalType": "address",
        "name": "artistAddress",
        "type": "address"
      }
    ],
    "name": "ArtistCreated",
    "type": "event"
  },
  {
    "anonymous": false,
    "inputs": [
      {
        "indexed": false,
        "internalType": "uint256",
        "name": "artistId",
        "type": "uint256"
      },
      {
        "indexed": false,
        "internalType": "string",
        "name": "name",
        "type": "string"
      },
      {
        "indexed": false,
        "internalType": "string",
        "name": "instagram",
        "type": "string"
      }
    ],
    "name": "ArtistUpdated",
    "type": "event"
  },
  {
    "anonymous": false,
    "inputs": [
      {
        "indexed": true,
        "internalType": "address",
        "name": "beacon",
        "type": "address"
      }
    ],
    "name": "BeaconUpgraded",
    "type": "event"
  },
  {
    "anonymous": false,
    "inputs": [
      {
        "indexed": false,
        "internalType": "address",
        "name": "config",
        "type": "address"
      }
    ],
    "name": "ConfigAddressChanged",
    "type": "event"
  },
  {
    "anonymous": false,
    "inputs": [
      {
        "indexed": true,
        "internalType": "address",
        "name": "previousOwner",
        "type": "address"
      },
      {
        "indexed": true,
        "internalType": "address",
        "name": "newOwner",
        "type": "address"
      }
    ],
    "name": "OwnershipTransferred",
    "type": "event"
  },
  {
    "anonymous": false,
    "inputs": [
      {
        "indexed": true,
        "internalType": "address",
        "name": "implementation",
        "type": "address"
      }
    ],
    "name": "Upgraded",
    "type": "event"
  },
  {
    "inputs": [
      {
        "internalType": "string",
        "name": "name",
        "type": "string"
      },
      {
        "internalType": "string",
        "name": "instagramId",
        "type": "string"
      },
      {
        "internalType": "string",
        "name": "instagram",
        "type": "string"
      },
      {
        "internalType": "bytes",
        "name": "signature1",
        "type": "bytes"
      },
      {
        "internalType": "bytes",
        "name": "signature2",
        "type": "bytes"
      }
    ],
    "name": "createArtist",
    "outputs": [
      {
        "internalType": "address",
        "name": "artistContractAddress",
        "type": "address"
      },
      {
        "internalType": "uint256",
        "name": "artistId",
        "type": "uint256"
      }
    ],
    "stateMutability": "payable",
    "type": "function"
  },
  {
    "inputs": [
      {
        "internalType": "address",
        "name": "account",
        "type": "address"
      },
      {
        "internalType": "string",
        "name": "name",
        "type": "string"
      },
      {
        "internalType": "string",
        "name": "instagramId",
        "type": "string"
      },
      {
        "internalType": "string",
        "name": "instagram",
        "type": "string"
      },
      {
        "internalType": "bytes",
        "name": "signature1",
        "type": "bytes"
      },
      {
        "internalType": "bytes",
        "name": "signature2",
        "type": "bytes"
      }
    ],
    "name": "createArtistRelay",
    "outputs": [
      {
        "internalType": "address",
        "name": "artistContractAddress",
        "type": "address"
      },
      {
        "internalType": "uint256",
        "name": "artistId",
        "type": "uint256"
      }
    ],
    "stateMutability": "nonpayable",
    "type": "function"
  },
  {
    "inputs": [
      {
        "internalType": "uint256",
        "name": "artistId",
        "type": "uint256"
      }
    ],
    "name": "getArtistContract",
    "outputs": [
      {
        "internalType": "address",
        "name": "",
        "type": "address"
      }
    ],
    "stateMutability": "view",
    "type": "function"
  },
  {
    "inputs": [
      {
        "internalType": "string",
        "name": "instagramId",
        "type": "string"
      }
    ],
    "name": "getArtistContractByInstagramId",
    "outputs": [
      {
        "internalType": "address",
        "name": "",
        "type": "address"
      }
    ],
    "stateMutability": "view",
    "type": "function"
  },
  {
    "inputs": [
      {
        "internalType": "string",
        "name": "instagramId",
        "type": "string"
      }
    ],
    "name": "getArtistId",
    "outputs": [
      {
        "internalType": "uint256",
        "name": "",
        "type": "uint256"
      }
    ],
    "stateMutability": "view",
    "type": "function"
  },
  {
    "inputs": [],
    "name": "getBeacon",
    "outputs": [
      {
        "internalType": "address",
        "name": "",
        "type": "address"
      }
    ],
    "stateMutability": "view",
    "type": "function"
  },
  {
    "inputs": [],
    "name": "getConfig",
    "outputs": [
      {
        "internalType": "address",
        "name": "",
        "type": "address"
      }
    ],
    "stateMutability": "view",
    "type": "function"
  },
  {
    "inputs": [],
    "name": "getCreationPrice",
    "outputs": [
      {
        "internalType": "uint256",
        "name": "",
        "type": "uint256"
      }
    ],
    "stateMutability": "view",
    "type": "function"
  },
  {
    "inputs": [
      {
        "internalType": "bytes",
        "name": "signature",
        "type": "bytes"
      },
      {
        "internalType": "uint256",
        "name": "signer",
        "type": "uint256"
      },
      {
        "internalType": "address",
        "name": "account",
        "type": "address"
      },
      {
        "internalType": "string",
        "name": "instagramId",
        "type": "string"
      },
      {
        "internalType": "string",
        "name": "instagram",
        "type": "string"
      }
    ],
    "name": "getSigner",
    "outputs": [
      {
        "internalType": "address",
        "name": "",
        "type": "address"
      }
    ],
    "stateMutability": "view",
    "type": "function"
  },
  {
    "inputs": [],
    "name": "getTokenPrice",
    "outputs": [
      {
        "internalType": "uint256",
        "name": "",
        "type": "uint256"
      }
    ],
    "stateMutability": "view",
    "type": "function"
  },
  {
    "inputs": [
      {
        "internalType": "address",
        "name": "config_",
        "type": "address"
      },
      {
        "internalType": "address",
        "name": "nftContract",
        "type": "address"
      },
      {
        "internalType": "uint256",
        "name": "tokenPrice",
        "type": "uint256"
      }
    ],
    "name": "initialize",
    "outputs": [],
    "stateMutability": "nonpayable",
    "type": "function"
  },
  {
    "inputs": [
      {
        "internalType": "address",
        "name": "account",
        "type": "address"
      }
    ],
    "name": "isAdmin",
    "outputs": [
      {
        "internalType": "bool",
        "name": "",
        "type": "bool"
      }
    ],
    "stateMutability": "view",
    "type": "function"
  },
  {
    "inputs": [],
    "name": "owner",
    "outputs": [
      {
        "internalType": "address",
        "name": "",
        "type": "address"
      }
    ],
    "stateMutability": "view",
    "type": "function"
  },
  {
    "inputs": [],
    "name": "proxiableUUID",
    "outputs": [
      {
        "internalType": "bytes32",
        "name": "",
        "type": "bytes32"
      }
    ],
    "stateMutability": "view",
    "type": "function"
  },
  {
    "inputs": [],
    "name": "renounceOwnership",
    "outputs": [],
    "stateMutability": "nonpayable",
    "type": "function"
  },
  {
    "inputs": [
      {
        "internalType": "address",
        "name": "config_",
        "type": "address"
      }
    ],
    "name": "setConfig",
    "outputs": [],
    "stateMutability": "nonpayable",
    "type": "function"
  },
  {
    "inputs": [
      {
        "internalType": "uint256",
        "name": "cents",
        "type": "uint256"
      }
    ],
    "name": "setTokenPrice",
    "outputs": [],
    "stateMutability": "nonpayable",
    "type": "function"
  },
  {
    "inputs": [
      {
        "internalType": "address",
        "name": "newOwner",
        "type": "address"
      }
    ],
    "name": "transferOwnership",
    "outputs": [],
    "stateMutability": "nonpayable",
    "type": "function"
  },
  {
    "inputs": [
      {
        "internalType": "uint256",
        "name": "artistId",
        "type": "uint256"
      },
      {
        "internalType": "string",
        "name": "name",
        "type": "string"
      },
      {
        "internalType": "string",
        "name": "instagram",
        "type": "string"
      },
      {
        "internalType": "bytes",
        "name": "signature1",
        "type": "bytes"
      },
      {
        "internalType": "bytes",
        "name": "signature2",
        "type": "bytes"
      }
    ],
    "name": "updateArtist",
    "outputs": [],
    "stateMutability": "nonpayable",
    "type": "function"
  },
  {
    "inputs": [
      {
        "internalType": "address",
        "name": "_newImplementation",
        "type": "address"
      }
    ],
    "name": "upgradeBeacon",
    "outputs": [],
    "stateMutability": "nonpayable",
    "type": "function"
  },
  {
    "inputs": [
      {
        "internalType": "address",
        "name": "newImplementation",
        "type": "address"
      }
    ],
    "name": "upgradeTo",
    "outputs": [],
    "stateMutability": "nonpayable",
    "type": "function"
  },
  {
    "inputs": [
      {
        "internalType": "address",
        "name": "newImplementation",
        "type": "address"
      },
      {
        "internalType": "bytes",
        "name": "data",
        "type": "bytes"
      }
    ],
    "name": "upgradeToAndCall",
    "outputs": [],
    "stateMutability": "payable",
    "type": "function"
  },
  {
    "inputs": [],
    "name": "version",
    "outputs": [
      {
        "internalType": "string",
        "name": "",
        "type": "string"
      }
    ],
    "stateMutability": "view",
    "type": "function"
  }
]
